{"int":{"st":"ESERCIZIO","t_ele":"Regionali Speciali","f_elet":"SCRUTINI","dt_ele":20241027000000,"l_terr":"SEZIONE","area":"I","desc_sez":"SEZIONE 30","cod_sez":30,"desc_com":"SANREMO","cod_com":520,"desc_prov":"IMPERIA","cod_prov":37,"ele_m":240,"ele_f":286,"ele_t":526,"vot_m":55,"vot_f":74,"vot_t":129,"perc_vot":"24,52","sz_pres":1,"sz_cons":1,"sz_tot":1,"fine_rip":null,"sk_bianche":0,"sk_nulle":2,"sk_contestate":0,"tot_vot_cand":127,"tot_vot_lis":117,"non_valid":null,"dt_agg":20241028171546,"data_prec_elez":null,"osp":"N","reg_sto":null,"prov_sto":null,"comu_sto":null,"circ_sto":null,"sez_sto":null},"note":["Non è previsto il dato retrospettivo a livello di sezione."],"cand":[{"cogn":"BUCCI","nome":"MARCO","a_nome":null,"d_nasc":19591031000000,"l_nasc":"GENOVA","pos":8,"desc_lis_r":null,"img_lis_r":null,"voti":66,"perc":"51,97","tot_vot_lis":58,"perc_lis":"49,57","liste":[{"pos":2,"desc_lis_c":"GIORGIA MELONI PER BUCCI PRESIDENTE FRATELLI D'ITALIA","img_lis_c":"7-20241027000000-2-037.png","voti":38,"perc":"32,48"},{"pos":14,"desc_lis_c":"LEGA LIGURIA BUCCI PRESIDENTE","img_lis_c":"7-20241027000000-14-037.png","voti":8,"perc":"6,84"},{"pos":15,"desc_lis_c":"FORZA ITALIA BERLUSCONI BUCCI PRESIDENTE PPE","img_lis_c":"7-20241027000000-15-037.png","voti":5,"perc":"4,27"},{"pos":3,"desc_lis_c":"ORGOGLIO LIGURIA BUCCI PRESIDENTE","img_lis_c":"7-20241027000000-3-037.png","voti":3,"perc":"2,56"},{"pos":1,"desc_lis_c":"BUCCI PRESIDENTE VINCE LIGURIA","img_lis_c":"7-20241027000000-1-037.png","voti":3,"perc":"2,56"},{"pos":13,"desc_lis_c":"BUCCI LIBERTAS UDC","img_lis_c":"7-20241027000000-13-037.png","voti":1,"perc":"0,85"},{"pos":10,"desc_lis_c":"ALTERNATIVA POPOLARE CON BANDECCHI PER BUCCI PPE","img_lis_c":"7-20241027000000-10-037.png","voti":0,"perc":"0"}]},{"cogn":"ORLANDO","nome":"ANDREA","a_nome":null,"d_nasc":19690208000000,"l_nasc":"LA SPEZIA","pos":9,"desc_lis_r":null,"img_lis_r":null,"voti":57,"perc":"44,88","tot_vot_lis":55,"perc_lis":"47,01","liste":[{"pos":5,"desc_lis_c":"PARTITO DEMOCRATICO ANDREA ORLANDO PRESIDENTE","img_lis_c":"7-20241027000000-5-037.png","voti":25,"perc":"21,37"},{"pos":16,"desc_lis_c":"ALLEANZA VERDI E SINISTRA - LISTA SANSA - POSSIBILE - EUROPA VERDE - SINISTRA ITALIANA","img_lis_c":"7-20241027000000-16-037.png","voti":16,"perc":"13,68"},{"pos":4,"desc_lis_c":"MOVIMENTO 5 STELLE 2050","img_lis_c":"7-20241027000000-4-037.png","voti":7,"perc":"5,98"},{"pos":11,"desc_lis_c":"LISTA ANDREA ORLANDO PRESIDENTE","img_lis_c":"7-20241027000000-11-037.png","voti":6,"perc":"5,13"},{"pos":6,"desc_lis_c":"LIGURI A TESTA ALTA ORLANDO PRESIDENTE","img_lis_c":"7-20241027000000-6-037.png","voti":1,"perc":"0,85"},{"pos":17,"desc_lis_c":"PATTO CIVICO E RIFORMISTA PER ORLANDO - AZIONE CON CALENDA - PRI - REPUBBLICANI EUROPEI - PER - ALLEANZA CIVICA LIGURIA","img_lis_c":"7-20241027000000-17-037.png","voti":0,"perc":"0"}]},{"cogn":"TOSCANO","nome":"FRANCESCO","a_nome":null,"d_nasc":19790528000000,"l_nasc":"GIOIA TAURO (RC)","pos":3,"desc_lis_r":null,"img_lis_r":null,"voti":3,"perc":"2,36","tot_vot_lis":3,"perc_lis":"2,56","liste":[{"pos":9,"desc_lis_c":"DEMOCRAZIA SOVRANA POPOLARE","img_lis_c":"7-20241027000000-9-037.png","voti":3,"perc":"2,56"}]},{"cogn":"FELICE","nome":"DAVIDE","a_nome":null,"d_nasc":19871129000000,"l_nasc":"BRESCIA","pos":2,"desc_lis_r":null,"img_lis_r":null,"voti":1,"perc":"0,79","tot_vot_lis":1,"perc_lis":"0,85","liste":[{"pos":18,"desc_lis_c":"FORZA DEL POPOLO","img_lis_c":"7-20241027000000-18-037.png","voti":1,"perc":"0,85"}]},{"cogn":"ROSSON","nome":"ALESSANDRO","a_nome":null,"d_nasc":19670421000000,"l_nasc":"LEVANTO (SP)","pos":1,"desc_lis_r":null,"img_lis_r":null,"voti":0,"perc":"0","tot_vot_lis":0,"perc_lis":"0","liste":[{"pos":8,"desc_lis_c":"INDIPENDENZA! ALEMANNO PER ROSSON","img_lis_c":"7-20241027000000-8-037.png","voti":0,"perc":"0"}]},{"cogn":"FERRANDO","nome":"MARCO GIUSEPPE","a_nome":null,"d_nasc":19540718000000,"l_nasc":"GENOVA","pos":4,"desc_lis_r":null,"img_lis_r":null,"voti":0,"perc":"0","tot_vot_lis":0,"perc_lis":"0","liste":[{"pos":null,"desc_lis_c":null,"img_lis_c":null,"voti":null,"perc":"0"}]},{"cogn":"ROLLANDO","nome":"NICOLA","a_nome":null,"d_nasc":19600907000000,"l_nasc":"SESTRI LEVANTE (GE)","pos":5,"desc_lis_r":null,"img_lis_r":null,"voti":0,"perc":"0","tot_vot_lis":0,"perc_lis":"0","liste":[{"pos":7,"desc_lis_c":"PER L'ALTERNATIVA - POTERE AL POPOLO! - PCI - RIFONDAZIONE PARTITO COMUNISTA SINISTRA EUROPEA","img_lis_c":"7-20241027000000-7-037.png","voti":0,"perc":"0"}]},{"cogn":"CELLA","nome":"MARIA ANTONIETTA","a_nome":null,"d_nasc":19641025000000,"l_nasc":"SANTO STEFANO D'AVETO (GE)","pos":6,"desc_lis_r":null,"img_lis_r":null,"voti":0,"perc":"0","tot_vot_lis":0,"perc_lis":"0","liste":[{"pos":19,"desc_lis_c":"PARTITO POPOLARE DEL NORD AUTONOMIA E LIBERTA'","img_lis_c":"7-20241027000000-19-037.png","voti":0,"perc":"0"}]},{"cogn":"MORRA","nome":"NICOLA","a_nome":null,"d_nasc":19630705000000,"l_nasc":"GENOVA","pos":7,"desc_lis_r":null,"img_lis_r":null,"voti":0,"perc":"0","tot_vot_lis":0,"perc_lis":"0","liste":[{"pos":12,"desc_lis_c":"UNITI PER LA COSTITUZIONE","img_lis_c":"7-20241027000000-12-037.png","voti":0,"perc":"0"}]}]}
