{"int":{"st":"ESERCIZIO","c_ele":7,"t_ele":"Regionali Speciali","f_elet":"VOTANTI","dt_ele":20241027000000,"l_terr":"COMUNE","area":"I","dt_agg":20241028151028},"note":["La percentuale riportata nella colonna della precedente elezione è sempre riferita a tutte le sezioni del comune.","Non è previsto il dato retrospettivo a livello di sezione."],"enti":{"ente_p":{"desc":"LERICI","cod":160,"ele_m":4245,"ele_f":4583,"ele_t":8828,"com":[{"cod_reg":7,"com_att":4,"num_com":4}],"com_vot":[{"com":1,"dt_com":20241027120000,"enti_p":13,"enti_t":13,"perc":"14,35","vot_m":0,"vot_f":0,"vot_t":1267,"perc_r":"13,08"},{"com":2,"dt_com":20241027190000,"enti_p":13,"enti_t":13,"perc":"34,45","vot_m":0,"vot_f":0,"vot_t":3041,"perc_r":"33,59"},{"com":3,"dt_com":20241027230000,"enti_p":13,"enti_t":13,"perc":"39,34","vot_m":0,"vot_f":0,"vot_t":3473,"perc_r":"45,87"},{"com":4,"dt_com":20241028150000,"enti_p":13,"enti_t":13,"perc":"51,13","vot_m":2175,"vot_f":2339,"vot_t":4514,"perc_r":"64,23"}]},"enti_f":[{"tipo":"SEZIONE","desc":"SEZIONE 1","cod":1,"osp":"N","ele_m":468,"ele_f":511,"ele_t":979,"com_vot":[{"com":1,"dt_com":20241027120000,"enti_p":1,"enti_t":1,"perc":"12,56","vot_m":0,"vot_f":0,"vot_t":123,"perc_r":null},{"com":2,"dt_com":20241027190000,"enti_p":1,"enti_t":1,"perc":"27,99","vot_m":0,"vot_f":0,"vot_t":274,"perc_r":null},{"com":3,"dt_com":20241027230000,"enti_p":1,"enti_t":1,"perc":"31,87","vot_m":0,"vot_f":0,"vot_t":312,"perc_r":null},{"com":4,"dt_com":20241028150000,"enti_p":1,"enti_t":1,"perc":"43,51","vot_m":192,"vot_f":234,"vot_t":426,"perc_r":null}]},{"tipo":"SEZIONE","desc":"SEZIONE 2","cod":2,"osp":"N","ele_m":399,"ele_f":444,"ele_t":843,"com_vot":[{"com":1,"dt_com":20241027120000,"enti_p":1,"enti_t":1,"perc":"12,69","vot_m":0,"vot_f":0,"vot_t":107,"perc_r":null},{"com":2,"dt_com":20241027190000,"enti_p":1,"enti_t":1,"perc":"32,15","vot_m":0,"vot_f":0,"vot_t":271,"perc_r":null},{"com":3,"dt_com":20241027230000,"enti_p":1,"enti_t":1,"perc":"37,37","vot_m":0,"vot_f":0,"vot_t":315,"perc_r":null},{"com":4,"dt_com":20241028150000,"enti_p":1,"enti_t":1,"perc":"48,28","vot_m":184,"vot_f":223,"vot_t":407,"perc_r":null}]},{"tipo":"SEZIONE","desc":"SEZIONE 3","cod":3,"osp":"N","ele_m":352,"ele_f":360,"ele_t":712,"com_vot":[{"com":1,"dt_com":20241027120000,"enti_p":1,"enti_t":1,"perc":"16,15","vot_m":0,"vot_f":0,"vot_t":115,"perc_r":null},{"com":2,"dt_com":20241027190000,"enti_p":1,"enti_t":1,"perc":"36,24","vot_m":0,"vot_f":0,"vot_t":258,"perc_r":null},{"com":3,"dt_com":20241027230000,"enti_p":1,"enti_t":1,"perc":"40,03","vot_m":0,"vot_f":0,"vot_t":285,"perc_r":null},{"com":4,"dt_com":20241028150000,"enti_p":1,"enti_t":1,"perc":"53,37","vot_m":182,"vot_f":198,"vot_t":380,"perc_r":null}]},{"tipo":"SEZIONE","desc":"SEZIONE 4","cod":4,"osp":"N","ele_m":339,"ele_f":350,"ele_t":689,"com_vot":[{"com":1,"dt_com":20241027120000,"enti_p":1,"enti_t":1,"perc":"16,11","vot_m":0,"vot_f":0,"vot_t":111,"perc_r":null},{"com":2,"dt_com":20241027190000,"enti_p":1,"enti_t":1,"perc":"39,04","vot_m":0,"vot_f":0,"vot_t":269,"perc_r":null},{"com":3,"dt_com":20241027230000,"enti_p":1,"enti_t":1,"perc":"44,99","vot_m":0,"vot_f":0,"vot_t":310,"perc_r":null},{"com":4,"dt_com":20241028150000,"enti_p":1,"enti_t":1,"perc":"55,01","vot_m":182,"vot_f":197,"vot_t":379,"perc_r":null}]},{"tipo":"SEZIONE","desc":"SEZIONE 5","cod":5,"osp":"N","ele_m":46,"ele_f":31,"ele_t":77,"com_vot":[{"com":1,"dt_com":20241027120000,"enti_p":1,"enti_t":1,"perc":"12,99","vot_m":0,"vot_f":0,"vot_t":10,"perc_r":null},{"com":2,"dt_com":20241027190000,"enti_p":1,"enti_t":1,"perc":"25,97","vot_m":0,"vot_f":0,"vot_t":20,"perc_r":null},{"com":3,"dt_com":20241027230000,"enti_p":1,"enti_t":1,"perc":"25,97","vot_m":0,"vot_f":0,"vot_t":20,"perc_r":null},{"com":4,"dt_com":20241028150000,"enti_p":1,"enti_t":1,"perc":"45,45","vot_m":21,"vot_f":14,"vot_t":35,"perc_r":null}]},{"tipo":"SEZIONE","desc":"SEZIONE 6","cod":6,"osp":"N","ele_m":234,"ele_f":258,"ele_t":492,"com_vot":[{"com":1,"dt_com":20241027120000,"enti_p":1,"enti_t":1,"perc":"15,45","vot_m":0,"vot_f":0,"vot_t":76,"perc_r":null},{"com":2,"dt_com":20241027190000,"enti_p":1,"enti_t":1,"perc":"42,48","vot_m":0,"vot_f":0,"vot_t":209,"perc_r":null},{"com":3,"dt_com":20241027230000,"enti_p":1,"enti_t":1,"perc":"45,93","vot_m":0,"vot_f":0,"vot_t":226,"perc_r":null},{"com":4,"dt_com":20241028150000,"enti_p":1,"enti_t":1,"perc":"57,11","vot_m":145,"vot_f":136,"vot_t":281,"perc_r":null}]},{"tipo":"SEZIONE","desc":"SEZIONE 7","cod":7,"osp":"N","ele_m":375,"ele_f":382,"ele_t":757,"com_vot":[{"com":1,"dt_com":20241027120000,"enti_p":1,"enti_t":1,"perc":"14,53","vot_m":0,"vot_f":0,"vot_t":110,"perc_r":null},{"com":2,"dt_com":20241027190000,"enti_p":1,"enti_t":1,"perc":"31,70","vot_m":0,"vot_f":0,"vot_t":240,"perc_r":null},{"com":3,"dt_com":20241027230000,"enti_p":1,"enti_t":1,"perc":"36,72","vot_m":0,"vot_f":0,"vot_t":278,"perc_r":null},{"com":4,"dt_com":20241028150000,"enti_p":1,"enti_t":1,"perc":"48,35","vot_m":174,"vot_f":192,"vot_t":366,"perc_r":null}]},{"tipo":"SEZIONE","desc":"SEZIONE 8","cod":8,"osp":"N","ele_m":324,"ele_f":355,"ele_t":679,"com_vot":[{"com":1,"dt_com":20241027120000,"enti_p":1,"enti_t":1,"perc":"11,78","vot_m":0,"vot_f":0,"vot_t":80,"perc_r":null},{"com":2,"dt_com":20241027190000,"enti_p":1,"enti_t":1,"perc":"36,38","vot_m":0,"vot_f":0,"vot_t":247,"perc_r":null},{"com":3,"dt_com":20241027230000,"enti_p":1,"enti_t":1,"perc":"39,91","vot_m":0,"vot_f":0,"vot_t":271,"perc_r":null},{"com":4,"dt_com":20241028150000,"enti_p":1,"enti_t":1,"perc":"51,25","vot_m":169,"vot_f":179,"vot_t":348,"perc_r":null}]},{"tipo":"SEZIONE","desc":"SEZIONE 9","cod":9,"osp":"N","ele_m":209,"ele_f":244,"ele_t":453,"com_vot":[{"com":1,"dt_com":20241027120000,"enti_p":1,"enti_t":1,"perc":"11,04","vot_m":0,"vot_f":0,"vot_t":50,"perc_r":null},{"com":2,"dt_com":20241027190000,"enti_p":1,"enti_t":1,"perc":"32,01","vot_m":0,"vot_f":0,"vot_t":145,"perc_r":null},{"com":3,"dt_com":20241027230000,"enti_p":1,"enti_t":1,"perc":"40,62","vot_m":0,"vot_f":0,"vot_t":184,"perc_r":null},{"com":4,"dt_com":20241028150000,"enti_p":1,"enti_t":1,"perc":"54,53","vot_m":118,"vot_f":129,"vot_t":247,"perc_r":null}]},{"tipo":"SEZIONE","desc":"SEZIONE 10","cod":10,"osp":"N","ele_m":353,"ele_f":350,"ele_t":703,"com_vot":[{"com":1,"dt_com":20241027120000,"enti_p":1,"enti_t":1,"perc":"15,65","vot_m":0,"vot_f":0,"vot_t":110,"perc_r":null},{"com":2,"dt_com":20241027190000,"enti_p":1,"enti_t":1,"perc":"38,12","vot_m":0,"vot_f":0,"vot_t":268,"perc_r":null},{"com":3,"dt_com":20241027230000,"enti_p":1,"enti_t":1,"perc":"45,23","vot_m":0,"vot_f":0,"vot_t":318,"perc_r":null},{"com":4,"dt_com":20241028150000,"enti_p":1,"enti_t":1,"perc":"56,19","vot_m":195,"vot_f":200,"vot_t":395,"perc_r":null}]},{"tipo":"SEZIONE","desc":"SEZIONE 11","cod":11,"osp":"N","ele_m":372,"ele_f":396,"ele_t":768,"com_vot":[{"com":1,"dt_com":20241027120000,"enti_p":1,"enti_t":1,"perc":"16,67","vot_m":0,"vot_f":0,"vot_t":128,"perc_r":null},{"com":2,"dt_com":20241027190000,"enti_p":1,"enti_t":1,"perc":"37,63","vot_m":0,"vot_f":0,"vot_t":289,"perc_r":null},{"com":3,"dt_com":20241027230000,"enti_p":1,"enti_t":1,"perc":"41,80","vot_m":0,"vot_f":0,"vot_t":321,"perc_r":null},{"com":4,"dt_com":20241028150000,"enti_p":1,"enti_t":1,"perc":"51,17","vot_m":197,"vot_f":196,"vot_t":393,"perc_r":null}]},{"tipo":"SEZIONE","desc":"SEZIONE 12","cod":12,"osp":"N","ele_m":406,"ele_f":505,"ele_t":911,"com_vot":[{"com":1,"dt_com":20241027120000,"enti_p":1,"enti_t":1,"perc":"14,27","vot_m":0,"vot_f":0,"vot_t":130,"perc_r":null},{"com":2,"dt_com":20241027190000,"enti_p":1,"enti_t":1,"perc":"33,48","vot_m":0,"vot_f":0,"vot_t":305,"perc_r":null},{"com":3,"dt_com":20241027230000,"enti_p":1,"enti_t":1,"perc":"37,98","vot_m":0,"vot_f":0,"vot_t":346,"perc_r":null},{"com":4,"dt_com":20241028150000,"enti_p":1,"enti_t":1,"perc":"50,16","vot_m":218,"vot_f":239,"vot_t":457,"perc_r":null}]},{"tipo":"SEZIONE","desc":"SEZIONE 13","cod":13,"osp":"N","ele_m":368,"ele_f":397,"ele_t":765,"com_vot":[{"com":1,"dt_com":20241027120000,"enti_p":1,"enti_t":1,"perc":"15,29","vot_m":0,"vot_f":0,"vot_t":117,"perc_r":null},{"com":2,"dt_com":20241027190000,"enti_p":1,"enti_t":1,"perc":"32,16","vot_m":0,"vot_f":0,"vot_t":246,"perc_r":null},{"com":3,"dt_com":20241027230000,"enti_p":1,"enti_t":1,"perc":"37,52","vot_m":0,"vot_f":0,"vot_t":287,"perc_r":null},{"com":4,"dt_com":20241028150000,"enti_p":1,"enti_t":1,"perc":"52,29","vot_m":198,"vot_f":202,"vot_t":400,"perc_r":null}]}]}}
