{"int":{"st":"ESERCIZIO","c_ele":7,"t_ele":"Regionali Speciali","f_elet":"VOTANTI","dt_ele":20241027000000,"l_terr":"COMUNE","area":"I","dt_agg":20241027190033},"note":["La percentuale riportata nella colonna della precedente elezione è sempre riferita a tutte le sezioni del comune.","Non è previsto il dato retrospettivo a livello di sezione."],"enti":{"ente_p":{"desc":"BALESTRINO","cod":80,"ele_m":310,"ele_f":323,"ele_t":633,"com":[{"cod_reg":7,"com_att":2,"num_com":4}],"com_vot":[{"com":1,"dt_com":20241027120000,"enti_p":1,"enti_t":1,"perc":"9,79","vot_m":0,"vot_f":0,"vot_t":62,"perc_r":"8,83"},{"com":2,"dt_com":20241027190000,"enti_p":1,"enti_t":1,"perc":"22,27","vot_m":0,"vot_f":0,"vot_t":141,"perc_r":"27,61"},{"com":3,"dt_com":20241027230000,"enti_p":0,"enti_t":1,"perc":"0","vot_m":0,"vot_f":0,"vot_t":0,"perc_r":"0"},{"com":4,"dt_com":20241028150000,"enti_p":0,"enti_t":1,"perc":"0","vot_m":0,"vot_f":0,"vot_t":0,"perc_r":"0"}]},"enti_f":[{"tipo":"SEZIONE","desc":"SEZIONE 1","cod":1,"osp":"N","ele_m":310,"ele_f":323,"ele_t":633,"com_vot":[{"com":1,"dt_com":20241027120000,"enti_p":1,"enti_t":1,"perc":"9,79","vot_m":0,"vot_f":0,"vot_t":62,"perc_r":null},{"com":2,"dt_com":20241027190000,"enti_p":1,"enti_t":1,"perc":"22,27","vot_m":0,"vot_f":0,"vot_t":141,"perc_r":null},{"com":3,"dt_com":20241027230000,"enti_p":0,"enti_t":1,"perc":"0","vot_m":0,"vot_f":0,"vot_t":0,"perc_r":null},{"com":4,"dt_com":20241028150000,"enti_p":0,"enti_t":1,"perc":"0","vot_m":0,"vot_f":0,"vot_t":0,"perc_r":null}]}]}}
